irmin/__init__.py
irmin/bindings.py
irmin/irmin.py
irmin-0.3.3.dist-info/LICENSE.md
irmin-0.3.3.dist-info/WHEEL
irmin-0.3.3.dist-info/METADATA
irmin-0.3.3.dist-info/RECORD
