Metadata-Version: 2.1
Name: irmin
Version: 0.3.3
Summary: Irmin bindings for Python
Home-page: https://github.com/mirage/irmin-py
License: ISC
Author: Zach Shipko
Author-email: zachshipko@gmail.com
Requires-Python: >=3.7,<4.0
Classifier: License :: OSI Approved
Classifier: Programming Language :: Python :: 3
Classifier: Programming Language :: Python :: 3.10
Classifier: Programming Language :: Python :: 3.7
Classifier: Programming Language :: Python :: 3.8
Classifier: Programming Language :: Python :: 3.9
Requires-Dist: cffi (>=1.15.0,<2.0.0)
Project-URL: Repository, https://github.com/mirage/irmin-py
